odoo/addons/product_pricelist_item_uom/README.rst
odoo/addons/product_pricelist_item_uom/__init__.py
odoo/addons/product_pricelist_item_uom/__manifest__.py
odoo/addons/product_pricelist_item_uom/i18n/it.po
odoo/addons/product_pricelist_item_uom/i18n/product_pricelist_item_uom.pot
odoo/addons/product_pricelist_item_uom/models/__init__.py
odoo/addons/product_pricelist_item_uom/models/product_pricelist_item.py
odoo/addons/product_pricelist_item_uom/readme/CONFIGURE.rst
odoo/addons/product_pricelist_item_uom/readme/CONTRIBUTORS.rst
odoo/addons/product_pricelist_item_uom/readme/DESCRIPTION.rst
odoo/addons/product_pricelist_item_uom/readme/USAGE.rst
odoo/addons/product_pricelist_item_uom/static/description/icon.png
odoo/addons/product_pricelist_item_uom/static/description/index.html
odoo/addons/product_pricelist_item_uom/tests/__init__.py
odoo/addons/product_pricelist_item_uom/tests/test_product_pricelist_item.py
odoo/addons/product_pricelist_item_uom/views/product_pricelist_item_views.xml
odoo/addons/product_pricelist_item_uom/views/product_pricelist_views.xml
odoo_addon_product_pricelist_item_uom-16.0.1.0.0.3.dist-info/METADATA
odoo_addon_product_pricelist_item_uom-16.0.1.0.0.3.dist-info/WHEEL
odoo_addon_product_pricelist_item_uom-16.0.1.0.0.3.dist-info/top_level.txt
odoo_addon_product_pricelist_item_uom-16.0.1.0.0.3.dist-info/RECORD
